pyinitlog_util/__init__.py
pyinitlog_util/pyinitlog_util.py
pyinitlog_util-1.0.0.dist-info/LICENSE
pyinitlog_util-1.0.0.dist-info/METADATA
pyinitlog_util-1.0.0.dist-info/WHEEL
pyinitlog_util-1.0.0.dist-info/top_level.txt
pyinitlog_util-1.0.0.dist-info/zip-safe
pyinitlog_util-1.0.0.dist-info/RECORD
