Metadata-Version: 2.1
Name: pyinitlog_util
Version: 1.0.0
Summary: logging的初始化
Home-page: https://github.com/buyfakett
Author: buyfakett
Author-email: buyfakett@vip.qq.com
License: MIT
Requires-Python: >=3.6
License-File: LICENSE
Requires-Dist: colorlog
